[
    {
        "video": "./video/galleryVideo01.mp4",
        "title": "The Ride",
        "description": "Istoria, Santorini, Greece"
    },
    {
        "video": "./video/galleryVideo02.mp4",
        "title": "The manhunt",
        "description": "Istoria, Santorini, Greece"
    },
    {
        "video": "./video/galleryVideo03.mp4",
        "title": "The primary",
        "description": "Istoria, Santorini, Greece"
    },
    {
        "video": "./video/galleryVideo05.mp4",
        "title": "The digging",
        "description": "Istoria, Santorini, Greece"
    },
    {
        "video": "./video/galleryVideo06.mp4",
        "title": "The because",
        "description": "Istoria, Santorini, Greece"
    },
    {
        "video": "./video/galleryVideo08.mp4",
        "title": "The bleakly",
        "description": "Istoria, Santorini, Greece"
    },
    {
        "video": "./video/galleryVideo09.mp4",
        "title": "The needily",
        "description": "Istoria, Santorini, Greece"
    },
    {
        "video": "./video/galleryVideo10.mp4",
        "title": "The whether",
        "description": "Istoria, Santorini, Greece"
    },
    {
        "video": "./video/galleryVideo11.mp4",
        "title": "The envious",
        "description": "Istoria, Santorini, Greece"
    },
    {
        "video": "./video/galleryVideo12.mp4",
        "title": "The huzzah",
        "description": "Istoria, Santorini, Greece"
    },
    {
        "video": "./video/galleryVideo13.mp4",
        "title": "The outline",
        "description": "Istoria, Santorini, Greece"
    },
    {
        "video": "./video/galleryVideo14.mp4",
        "title": "The yippee",
        "description": "Istoria, Santorini, Greece"
    },
    {
        "video": "./video/galleryVideo15.mp4",
        "title": "The student",
        "description": "Istoria, Santorini, Greece"
    },
    {
        "video": "./video/galleryVideo16.mp4",
        "title": "The reunify",
        "description": "Istoria, Santorini, Greece"
    },
    {
        "video": "./video/galleryVideo17.mp4",
        "title": "The bolster",
        "description": "Istoria, Santorini, Greece"
    }
]